{
	"configurations" : 
	[
		{
			"directories" : 
			[
				{
					"build" : ".",
					"jsonFile" : "directory-.-Debug-f5ebdc15457944623624.json",
					"minimumCMakeVersion" : 
					{
						"string" : "3.0.0"
					},
					"projectIndex" : 0,
					"source" : ".",
					"targetIndexes" : 
					[
						0,
						1,
						2,
						3,
						4,
						5,
						6,
						7,
						8,
						9,
						10,
						11,
						12,
						13,
						14,
						15,
						16,
						17,
						18,
						19,
						20,
						21,
						22,
						23,
						24,
						25,
						26,
						27,
						28
					]
				}
			],
			"name" : "Debug",
			"projects" : 
			[
				{
					"directoryIndexes" : 
					[
						0
					],
					"name" : "LuxPM",
					"targetIndexes" : 
					[
						0,
						1,
						2,
						3,
						4,
						5,
						6,
						7,
						8,
						9,
						10,
						11,
						12,
						13,
						14,
						15,
						16,
						17,
						18,
						19,
						20,
						21,
						22,
						23,
						24,
						25,
						26,
						27,
						28
					]
				}
			],
			"targets" : 
			[
				{
					"directoryIndex" : 0,
					"id" : "Continuous::@6890427a1f51a3e7e1df",
					"jsonFile" : "target-Continuous-Debug-bc9fa30678e92f1585cb.json",
					"name" : "Continuous",
					"projectIndex" : 0
				},
				{
					"directoryIndex" : 0,
					"id" : "ContinuousBuild::@6890427a1f51a3e7e1df",
					"jsonFile" : "target-ContinuousBuild-Debug-b4e3d21de271bf16c008.json",
					"name" : "ContinuousBuild",
					"projectIndex" : 0
				},
				{
					"directoryIndex" : 0,
					"id" : "ContinuousConfigure::@6890427a1f51a3e7e1df",
					"jsonFile" : "target-ContinuousConfigure-Debug-35483948b4de0d51e68f.json",
					"name" : "ContinuousConfigure",
					"projectIndex" : 0
				},
				{
					"directoryIndex" : 0,
					"id" : "ContinuousCoverage::@6890427a1f51a3e7e1df",
					"jsonFile" : "target-ContinuousCoverage-Debug-7d5156c5dcaae07adc31.json",
					"name" : "ContinuousCoverage",
					"projectIndex" : 0
				},
				{
					"directoryIndex" : 0,
					"id" : "ContinuousMemCheck::@6890427a1f51a3e7e1df",
					"jsonFile" : "target-ContinuousMemCheck-Debug-926b788ff10bd3ea1caf.json",
					"name" : "ContinuousMemCheck",
					"projectIndex" : 0
				},
				{
					"directoryIndex" : 0,
					"id" : "ContinuousStart::@6890427a1f51a3e7e1df",
					"jsonFile" : "target-ContinuousStart-Debug-a00d30465978c69505c1.json",
					"name" : "ContinuousStart",
					"projectIndex" : 0
				},
				{
					"directoryIndex" : 0,
					"id" : "ContinuousSubmit::@6890427a1f51a3e7e1df",
					"jsonFile" : "target-ContinuousSubmit-Debug-5ebb0b989c2d61ff06cb.json",
					"name" : "ContinuousSubmit",
					"projectIndex" : 0
				},
				{
					"directoryIndex" : 0,
					"id" : "ContinuousTest::@6890427a1f51a3e7e1df",
					"jsonFile" : "target-ContinuousTest-Debug-bbc62da86c1e757ad155.json",
					"name" : "ContinuousTest",
					"projectIndex" : 0
				},
				{
					"directoryIndex" : 0,
					"id" : "ContinuousUpdate::@6890427a1f51a3e7e1df",
					"jsonFile" : "target-ContinuousUpdate-Debug-d6f8f8ea044b42b4bce3.json",
					"name" : "ContinuousUpdate",
					"projectIndex" : 0
				},
				{
					"directoryIndex" : 0,
					"id" : "Experimental::@6890427a1f51a3e7e1df",
					"jsonFile" : "target-Experimental-Debug-f13268008a188f7250ca.json",
					"name" : "Experimental",
					"projectIndex" : 0
				},
				{
					"directoryIndex" : 0,
					"id" : "ExperimentalBuild::@6890427a1f51a3e7e1df",
					"jsonFile" : "target-ExperimentalBuild-Debug-9cb4e97ae1813ac8595a.json",
					"name" : "ExperimentalBuild",
					"projectIndex" : 0
				},
				{
					"directoryIndex" : 0,
					"id" : "ExperimentalConfigure::@6890427a1f51a3e7e1df",
					"jsonFile" : "target-ExperimentalConfigure-Debug-ea233f74940226c52dca.json",
					"name" : "ExperimentalConfigure",
					"projectIndex" : 0
				},
				{
					"directoryIndex" : 0,
					"id" : "ExperimentalCoverage::@6890427a1f51a3e7e1df",
					"jsonFile" : "target-ExperimentalCoverage-Debug-c03f917a41debabedd11.json",
					"name" : "ExperimentalCoverage",
					"projectIndex" : 0
				},
				{
					"directoryIndex" : 0,
					"id" : "ExperimentalMemCheck::@6890427a1f51a3e7e1df",
					"jsonFile" : "target-ExperimentalMemCheck-Debug-9e5b50f32138297ee06a.json",
					"name" : "ExperimentalMemCheck",
					"projectIndex" : 0
				},
				{
					"directoryIndex" : 0,
					"id" : "ExperimentalStart::@6890427a1f51a3e7e1df",
					"jsonFile" : "target-ExperimentalStart-Debug-26c185ba092a1eebee80.json",
					"name" : "ExperimentalStart",
					"projectIndex" : 0
				},
				{
					"directoryIndex" : 0,
					"id" : "ExperimentalSubmit::@6890427a1f51a3e7e1df",
					"jsonFile" : "target-ExperimentalSubmit-Debug-dcf2d031bdded6b3e756.json",
					"name" : "ExperimentalSubmit",
					"projectIndex" : 0
				},
				{
					"directoryIndex" : 0,
					"id" : "ExperimentalTest::@6890427a1f51a3e7e1df",
					"jsonFile" : "target-ExperimentalTest-Debug-921b4b21ed090b8fcdf4.json",
					"name" : "ExperimentalTest",
					"projectIndex" : 0
				},
				{
					"directoryIndex" : 0,
					"id" : "ExperimentalUpdate::@6890427a1f51a3e7e1df",
					"jsonFile" : "target-ExperimentalUpdate-Debug-4adb0d4406e60fe4a56a.json",
					"name" : "ExperimentalUpdate",
					"projectIndex" : 0
				},
				{
					"directoryIndex" : 0,
					"id" : "LuxPM::@6890427a1f51a3e7e1df",
					"jsonFile" : "target-LuxPM-Debug-f8bd826a585e39218a78.json",
					"name" : "LuxPM",
					"projectIndex" : 0
				},
				{
					"directoryIndex" : 0,
					"id" : "Nightly::@6890427a1f51a3e7e1df",
					"jsonFile" : "target-Nightly-Debug-4513796d1fcd7622751e.json",
					"name" : "Nightly",
					"projectIndex" : 0
				},
				{
					"directoryIndex" : 0,
					"id" : "NightlyBuild::@6890427a1f51a3e7e1df",
					"jsonFile" : "target-NightlyBuild-Debug-b54cd88aded1628a4407.json",
					"name" : "NightlyBuild",
					"projectIndex" : 0
				},
				{
					"directoryIndex" : 0,
					"id" : "NightlyConfigure::@6890427a1f51a3e7e1df",
					"jsonFile" : "target-NightlyConfigure-Debug-6a0f2cf5f01ba027cc51.json",
					"name" : "NightlyConfigure",
					"projectIndex" : 0
				},
				{
					"directoryIndex" : 0,
					"id" : "NightlyCoverage::@6890427a1f51a3e7e1df",
					"jsonFile" : "target-NightlyCoverage-Debug-5e7ec9ce0edde9eb38dd.json",
					"name" : "NightlyCoverage",
					"projectIndex" : 0
				},
				{
					"directoryIndex" : 0,
					"id" : "NightlyMemCheck::@6890427a1f51a3e7e1df",
					"jsonFile" : "target-NightlyMemCheck-Debug-6751990945a62e93ed87.json",
					"name" : "NightlyMemCheck",
					"projectIndex" : 0
				},
				{
					"directoryIndex" : 0,
					"id" : "NightlyMemoryCheck::@6890427a1f51a3e7e1df",
					"jsonFile" : "target-NightlyMemoryCheck-Debug-5346f41ecdeec7250a40.json",
					"name" : "NightlyMemoryCheck",
					"projectIndex" : 0
				},
				{
					"directoryIndex" : 0,
					"id" : "NightlyStart::@6890427a1f51a3e7e1df",
					"jsonFile" : "target-NightlyStart-Debug-68121267e697e59a3d36.json",
					"name" : "NightlyStart",
					"projectIndex" : 0
				},
				{
					"directoryIndex" : 0,
					"id" : "NightlySubmit::@6890427a1f51a3e7e1df",
					"jsonFile" : "target-NightlySubmit-Debug-4b46388ee240d4b9e859.json",
					"name" : "NightlySubmit",
					"projectIndex" : 0
				},
				{
					"directoryIndex" : 0,
					"id" : "NightlyTest::@6890427a1f51a3e7e1df",
					"jsonFile" : "target-NightlyTest-Debug-8783e8f007438e8afe79.json",
					"name" : "NightlyTest",
					"projectIndex" : 0
				},
				{
					"directoryIndex" : 0,
					"id" : "NightlyUpdate::@6890427a1f51a3e7e1df",
					"jsonFile" : "target-NightlyUpdate-Debug-dcfea2128a9d4f02b84d.json",
					"name" : "NightlyUpdate",
					"projectIndex" : 0
				}
			]
		}
	],
	"kind" : "codemodel",
	"paths" : 
	{
		"build" : "/Users/abhijeetdhupia/Documents/Coding/LuxPM/CPP/build",
		"source" : "/Users/abhijeetdhupia/Documents/Coding/LuxPM/CPP"
	},
	"version" : 
	{
		"major" : 2,
		"minor" : 3
	}
}
